scp_api_client/__init__.py
scp_api_client/api_client.py
scp_api_client-0.4.0.dist-info/LICENSE
scp_api_client-0.4.0.dist-info/METADATA
scp_api_client-0.4.0.dist-info/WHEEL
scp_api_client-0.4.0.dist-info/top_level.txt
scp_api_client-0.4.0.dist-info/RECORD
